fetchmesh/__init__.py
fetchmesh/alias/__init__.py
fetchmesh/alias/kapar.py
fetchmesh/atlas/__init__.py
fetchmesh/atlas/client.py
fetchmesh/atlas/objects.py
fetchmesh/bgp/__init__.py
fetchmesh/bgp/asnames.py
fetchmesh/bgp/asndb.py
fetchmesh/bgp/collectors.py
fetchmesh/commands/__init__.py
fetchmesh/commands/common.py
fetchmesh/commands/csv.py
fetchmesh/commands/describe.py
fetchmesh/commands/fetch.py
fetchmesh/commands/unpack.py
fetchmesh/commands/upgrade.py
fetchmesh/fetcher.py
fetchmesh/filters/__init__.py
fetchmesh/filters/abstract.py
fetchmesh/filters/anchor.py
fetchmesh/filters/measurement.py
fetchmesh/filters/record.py
fetchmesh/io.py
fetchmesh/mesh.py
fetchmesh/meta.py
fetchmesh/mocks/__init__.py
fetchmesh/mocks/anchors.json
fetchmesh/mocks/asn.txt
fetchmesh/mocks/bview.20190417.0800.gz
fetchmesh/mocks/dictionary
fetchmesh/mocks/ix.json
fetchmesh/mocks/ixlan.json
fetchmesh/mocks/ixpfx.json
fetchmesh/mocks/measurements.json
fetchmesh/mocks/results.ndjson
fetchmesh/mocks/rib.20180131.0800.bz2
fetchmesh/peeringdb/__init__.py
fetchmesh/peeringdb/client.py
fetchmesh/peeringdb/db.py
fetchmesh/peeringdb/objects.py
fetchmesh/transformers/__init__.py
fetchmesh/transformers/record.py
fetchmesh-0.3.3.dist-info/entry_points.txt
fetchmesh-0.3.3.dist-info/LICENSE
fetchmesh-0.3.3.dist-info/WHEEL
fetchmesh-0.3.3.dist-info/METADATA
fetchmesh-0.3.3.dist-info/RECORD
